pyline/__init__.py
pyline/pyline_cli.py
pyline_cli-0.0.1.dist-info/LICENSE
pyline_cli-0.0.1.dist-info/METADATA
pyline_cli-0.0.1.dist-info/WHEEL
pyline_cli-0.0.1.dist-info/top_level.txt
pyline_cli-0.0.1.dist-info/RECORD
