Metadata-Version: 2.1
Name: pyline-cli
Version: 0.0.1
Summary: Make easy CLI apps in python
Author: HeavyLvy
Maintainer: HeavyLvy
Project-URL: Repository, https://github.com/HeavyLvy/pyline
Keywords: python,cli
Classifier: License :: OSI Approved :: MIT License
Classifier: Development Status :: 2 - Pre-Alpha
Classifier: Intended Audience :: Developers
Classifier: Programming Language :: Python :: 3
Classifier: Operating System :: Unix
Classifier: Operating System :: MacOS :: MacOS X
Classifier: Operating System :: Microsoft :: Windows
License-File: LICENSE
Requires-Dist: fuzzywuzzy
